{
  "$schema": "../schema/fixture.schema.json",
  "name": "independent_component_analysis",
  "path": "independent_component_analysis.wasm",
  "wat": {
    "status": "present",
    "path": "independent_component_analysis.wat"
  },
  "features": [],
  "exports": [
    {
      "name": "memory",
      "kind": "memory",
      "type": "(memory 1)"
    },
    {
      "name": "independent_component_analysis",
      "kind": "function",
      "type": "(func (param i32 i32) (result i32))"
    }
  ],
  "tests": [
    {
      "description": "baseline",
      "steps": [
        {
          "type": "function.invoke",
          "function": "independent_component_analysis",
          "params": [
            {
              "type": "i32",
              "value": "0"
            },
            {
              "type": "i32",
              "value": "7"
            }
          ],
          "results": [
            {
              "type": "i32",
              "value": "2456"
            }
          ]
        }
      ]
    },
    {
      "description": "alternate-mode",
      "steps": [
        {
          "type": "function.invoke",
          "function": "independent_component_analysis",
          "params": [
            {
              "type": "i32",
              "value": "1"
            },
            {
              "type": "i32",
              "value": "13"
            }
          ],
          "results": [
            {
              "type": "i32",
              "value": "4474"
            }
          ]
        }
      ]
    },
    {
      "description": "low-input",
      "steps": [
        {
          "type": "function.invoke",
          "function": "independent_component_analysis",
          "params": [
            {
              "type": "i32",
              "value": "2"
            },
            {
              "type": "i32",
              "value": "3"
            }
          ],
          "results": [
            {
              "type": "i32",
              "value": "1453"
            }
          ]
        }
      ]
    }
  ],
  "sha256": "cacdc2026cddd537980aa577a20f04dc2f65a6532abc255b85780f566ec915b0",
  "source": {
    "contributor": "ai",
    "language": "wat",
    "description": "AI-authored WAT implementation of Independent Component Analysis for wasm-corpus fixed-dataset coverage."
  },
  "toolchain": {
    "name": "Binaryen",
    "version": "wasm-opt version 125",
    "command": "./scripts/prepare"
  },
  "description": "ICA non-Gaussianity contrast over fixed mixtures.",
  "tags": [
    "algorithm",
    "bounded-general",
    "machine-learning",
    "wat",
    "linear-algebra",
    "independent",
    "component",
    "analysis"
  ],
  "notes": "Bounded-general fixture for Independent Component Analysis. The implementation uses fixed in-module data and mode-selected branches/loops to exercise representative matrix behavior; it is intended as runtime corpus coverage rather than a production ML implementation."
}
