{
  "$schema": "../schema/fixture.schema.json",
  "name": "positional_encoding",
  "path": "positional_encoding.wasm",
  "wat": {
    "status": "present",
    "path": "positional_encoding.wat"
  },
  "features": [],
  "exports": [
    {
      "name": "memory",
      "kind": "memory",
      "type": "(memory 1)"
    },
    {
      "name": "positional_encoding",
      "kind": "function",
      "type": "(func (param i32 i32) (result i32))"
    }
  ],
  "tests": [
    {
      "description": "mode-zero-baseline",
      "steps": [
        {
          "type": "function.invoke",
          "function": "positional_encoding",
          "params": [
            {
              "type": "i32",
              "value": "0"
            },
            {
              "type": "i32",
              "value": "7"
            }
          ],
          "results": [
            {
              "type": "i32",
              "value": "4596"
            }
          ]
        }
      ]
    },
    {
      "description": "mode-one-alternate",
      "steps": [
        {
          "type": "function.invoke",
          "function": "positional_encoding",
          "params": [
            {
              "type": "i32",
              "value": "1"
            },
            {
              "type": "i32",
              "value": "13"
            }
          ],
          "results": [
            {
              "type": "i32",
              "value": "5348"
            }
          ]
        }
      ]
    },
    {
      "description": "mode-two-low-input",
      "steps": [
        {
          "type": "function.invoke",
          "function": "positional_encoding",
          "params": [
            {
              "type": "i32",
              "value": "2"
            },
            {
              "type": "i32",
              "value": "3"
            }
          ],
          "results": [
            {
              "type": "i32",
              "value": "3604"
            }
          ]
        }
      ]
    },
    {
      "description": "negative-input",
      "steps": [
        {
          "type": "function.invoke",
          "function": "positional_encoding",
          "params": [
            {
              "type": "i32",
              "value": "0"
            },
            {
              "type": "i32",
              "value": "-5"
            }
          ],
          "results": [
            {
              "type": "i32",
              "value": "2278"
            }
          ]
        }
      ]
    },
    {
      "description": "wide-input",
      "steps": [
        {
          "type": "function.invoke",
          "function": "positional_encoding",
          "params": [
            {
              "type": "i32",
              "value": "2"
            },
            {
              "type": "i32",
              "value": "42"
            }
          ],
          "results": [
            {
              "type": "i32",
              "value": "1414"
            }
          ]
        }
      ]
    }
  ],
  "sha256": "3ea89c5707cf61f043250f5cbd46f75b387a83b4817649d1f068361ae71b4c74",
  "source": {
    "contributor": "ai",
    "language": "wat",
    "description": "AI-authored WAT implementation of Positional encoding for wasm-corpus fixed-dataset coverage."
  },
  "toolchain": {
    "name": "Binaryen",
    "version": "wasm-opt version 125",
    "command": "./scripts/prepare"
  },
  "description": "Integer sinusoid-table positional encoding checksum.",
  "tags": [
    "algorithm",
    "bounded-general",
    "machine-learning",
    "wat",
    "sequence-model",
    "positional",
    "encoding"
  ],
  "notes": "Bounded-general fixture for Positional encoding. The implementation uses fixed in-module data and mode-selected branches/loops to exercise representative encoding behavior; tests cover all three modes plus negative and wider input cases. It is intended as runtime corpus coverage rather than a production ML implementation."
}
